sslmanager/__init__.py
sslmanager/cmd_add_alias.py
sslmanager/cmd_del_alias.py
sslmanager/cmd_help.py
sslmanager/cmd_init.py
sslmanager/cmd_list_alias.py
sslmanager/cmd_new_request.py
sslmanager/cmd_store_cert.py
sslmanager/cmd_upload.py
sslmanager/config.py
sslmanager/helper.py
sslmanager/main.py
sslmanager/plugin.py
sslmanager/print_helper.py
sslmanager/models/config.py
sslmanager/models/filenames.py
sslmanager/models/openssl_config.py
sslmanager/types/domain_name.py
sslmanager_sebastian_stigler-0.8.0.dist-info/licenses/LICENSE.txt
sslmanager_sebastian_stigler-0.8.0.dist-info/METADATA
sslmanager_sebastian_stigler-0.8.0.dist-info/WHEEL
sslmanager_sebastian_stigler-0.8.0.dist-info/entry_points.txt
sslmanager_sebastian_stigler-0.8.0.dist-info/top_level.txt
sslmanager_sebastian_stigler-0.8.0.dist-info/RECORD
