Metadata-Version: 2.4
Name: sslmanager-sebastian-stigler
Version: 0.8.0
Summary: Add a short description here!
Home-page: https://github.com/pyscaffold/pyscaffold/
Author: Sebastian Stigler
Author-email: sebastian.stigler@hs-aalen.de
License: MIT
Project-URL: Documentation, https://pyscaffold.org/
Platform: any
Classifier: Development Status :: 4 - Beta
Classifier: Programming Language :: Python
License-File: LICENSE.txt
Requires-Dist: importlib-metadata; python_version < "3.8"
Requires-Dist: coloredlogs==15.0.1
Requires-Dist: colorama==0.4.6
Requires-Dist: humanfriendly==10.0
Requires-Dist: inquirerpy==0.3.4
Requires-Dist: prompt_toolkit==3.0.48
Requires-Dist: wcwidth==0.2.13
Requires-Dist: annotated-types==0.7.0
Requires-Dist: pydantic==2.9.2
Requires-Dist: pydantic-core==2.23.4
Requires-Dist: typing-extensions==4.12.2
Requires-Dist: dnspython==2.7.0
Requires-Dist: email-validator==2.2.0
Requires-Dist: idna==3.10
Requires-Dist: shtab==1.7.1
Provides-Extra: testing
Requires-Dist: setuptools; extra == "testing"
Requires-Dist: pytest; extra == "testing"
Requires-Dist: pytest-cov; extra == "testing"
Dynamic: license-file
